kubra/__init__.py
kubra-0.1.4.dist-info/LICENSE
kubra-0.1.4.dist-info/METADATA
kubra-0.1.4.dist-info/WHEEL
kubra-0.1.4.dist-info/entry_points.txt
kubra-0.1.4.dist-info/top_level.txt
kubra-0.1.4.dist-info/RECORD
