Metadata-Version: 2.1
Name: kubra
Version: 0.1.4
Summary: command line tool for downloading utility outage data
Home-page: https://github.com/fgregg/kubra
Author: Forest Gregg
Author-email: fgregg@datamade.us
License-File: LICENSE
Requires-Dist: click
Requires-Dist: tqdm
Requires-Dist: scrapelib
Requires-Dist: polyline
Requires-Dist: mercantile
